testPipMK/__init__.py
testPipMK/m_modMK.py
testPipMK-0.0.1.dist-info/LICENSE.txt
testPipMK-0.0.1.dist-info/METADATA
testPipMK-0.0.1.dist-info/WHEEL
testPipMK-0.0.1.dist-info/top_level.txt
testPipMK-0.0.1.dist-info/RECORD
