Metadata-Version: 2.1
Name: testPipMK
Version: 0.0.1
Summary: My test packages
Author-email: MK <m.kobialka@healthpharm.pl>
License: MIT License
Keywords: testyPipMK,name,surname
Classifier: License :: OSI Approved :: GNU General Public License v3 or later (GPLv3+)
Classifier: License :: OSI Approved :: Python Software Foundation License
Requires-Python: >=3.0
License-File: LICENSE.txt
Requires-Dist: numpy
